opcua/__init__.py
opcua/compat.py
opcua/tools.py
opcua/client/__init__.py
opcua/client/client.py
opcua/client/ua_client.py
opcua/common/__init__.py
opcua/common/callback.py
opcua/common/connection.py
opcua/common/copy_node.py
opcua/common/event_objects.py
opcua/common/events.py
opcua/common/instantiate.py
opcua/common/manage_nodes.py
opcua/common/methods.py
opcua/common/node.py
opcua/common/shortcuts.py
opcua/common/structures.py
opcua/common/subscription.py
opcua/common/type_dictionary_buider.py
opcua/common/ua_utils.py
opcua/common/utils.py
opcua/common/utils_orig.py
opcua/common/xmlexporter.py
opcua/common/xmlimporter.py
opcua/common/xmlparser.py
opcua/crypto/__init__.py
opcua/crypto/security_policies.py
opcua/crypto/uacrypto.py
opcua/server/__init__.py
opcua/server/address_space.py
opcua/server/binary_server_asyncio.py
opcua/server/discovery_service.py
opcua/server/event_generator.py
opcua/server/history.py
opcua/server/history_sql.py
opcua/server/internal_server.py
opcua/server/internal_subscription.py
opcua/server/registration_service.py
opcua/server/server.py
opcua/server/subscription_service.py
opcua/server/uaprocessor.py
opcua/server/user_manager.py
opcua/server/standard_address_space/__init__.py
opcua/server/standard_address_space/standard_address_space.py
opcua/server/standard_address_space/standard_address_space_part10.py
opcua/server/standard_address_space/standard_address_space_part11.py
opcua/server/standard_address_space/standard_address_space_part13.py
opcua/server/standard_address_space/standard_address_space_part3.py
opcua/server/standard_address_space/standard_address_space_part4.py
opcua/server/standard_address_space/standard_address_space_part5.py
opcua/server/standard_address_space/standard_address_space_part8.py
opcua/server/standard_address_space/standard_address_space_part9.py
opcua/ua/__init__.py
opcua/ua/attribute_ids.py
opcua/ua/extension_objects.py
opcua/ua/object_ids.py
opcua/ua/status_codes.py
opcua/ua/ua_binary.py
samyplugin-0.1.dist-info/LICENSE
samyplugin-0.1.dist-info/METADATA
samyplugin-0.1.dist-info/WHEEL
samyplugin-0.1.dist-info/top_level.txt
samyplugin-0.1.dist-info/RECORD
