Metadata-Version: 2.1
Name: samyplugin
Version: 0.1
Summary: Samy plugin package.
Home-page: https://github.com/TW-Robotics/SAMYPlugins_Templates
Author: Felix Leber
Author-email: leber@technikum-wien.at
License: UNKNOWN
Platform: UNKNOWN
Classifier: Programming Language :: Python :: 3
Classifier: License :: OSI Approved :: MIT License
Classifier: Operating System :: OS Independent
Requires-Python: >=3.6
License-File: LICENSE
